fcm_receiver/__init__.py
fcm_receiver/cli.py
fcm_receiver/crypto_utils.py
fcm_receiver/exceptions.py
fcm_receiver/fcm_client.py
fcm_receiver/fcm_socket.py
fcm_receiver/http_client.py
fcm_receiver/marshal_manual.py
fcm_receiver/messages_manual.py
fcm_receiver/proto_manual.py
fcm_receiver/unmarshal_manual.py
fcm_receiver-0.1.1.dist-info/licenses/LICENSE
tests/__init__.py
tests/test_register_simple.py
fcm_receiver-0.1.1.dist-info/METADATA
fcm_receiver-0.1.1.dist-info/WHEEL
fcm_receiver-0.1.1.dist-info/entry_points.txt
fcm_receiver-0.1.1.dist-info/top_level.txt
fcm_receiver-0.1.1.dist-info/RECORD
