Metadata-Version: 2.4
Name: fcm-receiver
Version: 0.1.1
Summary: A Python library for receiving Firebase Cloud Messages
Home-page: https://github.com/agusibrahim/pyfcm-receiver
Author: Agus Ibrahim
Author-email: Agus Ibrahim <hello@agusibrah.im>
License: MIT
Classifier: Development Status :: 3 - Alpha
Classifier: Intended Audience :: Developers
Classifier: License :: OSI Approved :: MIT License
Classifier: Operating System :: OS Independent
Classifier: Programming Language :: Python :: 3
Classifier: Programming Language :: Python :: 3.7
Classifier: Programming Language :: Python :: 3.8
Classifier: Programming Language :: Python :: 3.9
Classifier: Programming Language :: Python :: 3.10
Classifier: Programming Language :: Python :: 3.11
Requires-Python: >=3.7
License-File: LICENSE
Requires-Dist: cryptography>=3.0.0
Requires-Dist: http-ece>=1.0.5
Requires-Dist: requests>=2.25.0
Requires-Dist: pycryptodome>=3.9.0
Provides-Extra: dev
Requires-Dist: pytest>=6.0; extra == "dev"
Requires-Dist: pytest-cov>=2.0; extra == "dev"
Requires-Dist: black>=21.0; extra == "dev"
Requires-Dist: flake8>=3.8; extra == "dev"
Requires-Dist: mypy>=0.900; extra == "dev"
Dynamic: author
Dynamic: home-page
Dynamic: license-file
Dynamic: requires-python
